Binomial_Dist
