Metadata-Version: 1.0
Name: Binomial-Dist
Version: 0.2
Summary: Binomial distributions
Home-page: UNKNOWN
Author: Taskin Mehereen
Author-email: mehereen256@gmail.com
License: UNKNOWN
Platform: UNKNOWN
